[
    {
        "description": "Ensures buttons have discernible text",
        "impact": "critical",
        "tags": [
            "cat.name-role-value",
            "wcag2a",
            "wcag412",
            "section508",
            "section508.22.a"
        ],
        "num_nodes_violated": 1
    },
    {
        "description": "Ensures the contrast between foreground and background colors meets WCAG 2 AA contrast ratio thresholds",
        "impact": "serious",
        "tags": [
            "cat.color",
            "wcag2aa",
            "wcag143"
        ],
        "num_nodes_violated": 10
    },
    {
        "description": "Ensures every id attribute value is unique",
        "impact": "minor",
        "tags": [
            "cat.parsing",
            "wcag2a",
            "wcag411"
        ],
        "num_nodes_violated": 4
    },
    {
        "description": "Ensure button and link text is not repeated as image alternative",
        "impact": "minor",
        "tags": [
            "cat.text-alternatives",
            "best-practice"
        ],
        "num_nodes_violated": 20
    },
    {
        "description": "Ensures every form element has a label",
        "impact": "critical",
        "tags": [
            "cat.forms",
            "wcag2a",
            "wcag332",
            "wcag131",
            "section508",
            "section508.22.n"
        ],
        "num_nodes_violated": 1
    },
    {
        "description": "Ensures links have discernible text",
        "impact": "serious",
        "tags": [
            "cat.name-role-value",
            "wcag2a",
            "wcag412",
            "wcag244",
            "section508",
            "section508.22.a"
        ],
        "num_nodes_violated": 8
    },
    {
        "description": "Ensures that lists are structured correctly",
        "impact": "serious",
        "tags": [
            "cat.structure",
            "wcag2a",
            "wcag131"
        ],
        "num_nodes_violated": 1
    }
]